GoogleTable.py
googletable-1.1.3.dist-info/METADATA
googletable-1.1.3.dist-info/WHEEL
googletable-1.1.3.dist-info/RECORD
