Metadata-Version: 2.1
Name: googletable
Version: 1.1.3
Summary: The module that collects data from the Google table
Keywords: Google,Table,Google Table,Google Sheets
Author: DaniEruDai
Author-email: DaniEruDai@gmail.com
Requires-Python: >=3,<4
Classifier: Programming Language :: Python :: 3
Classifier: Programming Language :: Python :: 3.4
Classifier: Programming Language :: Python :: 3.5
Classifier: Programming Language :: Python :: 3.6
Classifier: Programming Language :: Python :: 3.7
Classifier: Programming Language :: Python :: 3.8
Classifier: Programming Language :: Python :: 3.9
Classifier: Programming Language :: Python :: 3.10
Classifier: Programming Language :: Python :: 3.11
Requires-Dist: pandas (>=1.5.2,<2.0.0)
Requires-Dist: requests (>=2.28.1,<3.0.0)
